<?xml version="1.0" encoding="UTF-8"?>
<!DOCTYPE mapper PUBLIC "-//mybatis.org//DTD Mapper 3.0//EN" "http://mybatis.org/dtd/mybatis-3-mapper.dtd">

<mapper namespace="com.sql.ehr.external.dao.ApplicationDao">

	<!-- 可根据自己的需求，是否要使用 -->
    <resultMap type="com.sql.ehr.external.dto.ApplicationEntity" id="applicationMap">
        <result property="no" column="no"/>
        <result property="recruitNo" column="recruit_no"/>
        <result property="name" column="name"/>
        <result property="gender" column="gender"/>
        <result property="birthday" column="birthday"/>
        <result property="phone" column="phone"/>
        <result property="email" column="email"/>
        <result property="postNo" column="post_no"/>
        <result property="createTime" column="create_time"/>
        <result property="createUser" column="create_user"/>
        <result property="updateTime" column="update_time"/>
        <result property="updateUser" column="update_user"/>
    </resultMap>


</mapper>