<?xml version="1.0" encoding="UTF-8"?>
<!DOCTYPE mapper PUBLIC "-//mybatis.org//DTD Mapper 3.0//EN" "http://mybatis.org/dtd/mybatis-3-mapper.dtd">

<mapper namespace="com.sql.ehr.dao.ApplicationDao">

	<!-- 可根据自己的需求，是否要使用 -->
    <resultMap type="com.sql.ehr.entity.ApplicationEntity" id="applicationMap">
        <result property="ano" column="ano"/>
        <result property="aname" column="aname"/>
        <result property="agender" column="agender"/>
        <result property="abirthday" column="abirthday"/>
        <result property="aphone" column="aphone"/>
        <result property="aemail" column="aemail"/>
        <result property="apno" column="apno"/>
    </resultMap>


</mapper>